Workbook

Sheet README
A1: Caspr — one-time user segmentation export
A2: Requested 2026-08-18 · companion document: docs/gtm/segmentation-ask.md
A4: What to do
A5: 1. | B5: Fill in the 'User Export' sheet. One row per account, ALL accounts ever created.
A6: 2. | B6: Row 1 is the header. Row 2 is a worked EXAMPLE (yellow) — delete it or overwrite it.
A7: 3. | B7: Real data starts at row 3. Do not insert rows above row 3, and do not reorder columns.
A8: 4. | B8: Columns AE and AF are calculated automatically. Leave them alone.
A9: 5. | B9: 'Segment Summary' fills itself from your data. Nothing to do there.
A10: 6. | B10: 'Domain Clusters' needs a separate GROUP BY — see that sheet.
A12: Rules
A13: Blank vs zero | B13: Leave a cell BLANK if the value does not exist. Do not write 0, NULL or N/A. A blank and a zero mean different things to us.
A14: Dates | B14: ISO 8601 (YYYY-MM-DD). Real date cells or plain text both work.
A15: Booleans | B15: TRUE or FALSE.
A16: Do not filter | B16: Include test, internal and deleted accounts. Flag them in columns X and Y — we will exclude them ourselves.
A17: Approximate is fine | B17: If a field cannot be produced cleanly, give the closest proxy and tell us what it counts. An approximate number this week beats an exact one next month.
A19: Colour key
A20: Yellow | B20: Example row / cells for you to fill
A21: Grey | B21: Calculated automatically — do not edit
A23: Handling
B24: This file contains personal data for every person who has signed up for Caspr. Keep it on the shared drive, not on local machines. Do not upload it to any third-party tool.

Sheet User Export
A1: user_id | B1: email | C1: first_name | D1: last_name | E1: signup_date | F1: signup_source | G1: email_domain | H1: email_domain_type | I1: country | J1: last_login_date | K1: login_count | L1: prompts_started | M1: analyses_completed | N1: first_analysis_date | O1: last_analysis_date | P1: analyses_by_depth | Q1: reports_downloaded | R1: legacy_plan | S1: legacy_token_balance | T1: ever_paid | U1: total_revenue_to_date | V1: trial_balance_remaining | W1: trial_expiry_date | X1: account_status | Y1: is_internal_or_test | Z1: email_hard_bounced | AA1: unsubscribed | AB1: marketing_consent | AC1: consent_basis | AD1: consent_date | AE1: days_to_first_analysis | AF1: segment
A2: u_00417 | B2: priya.raman@brightlinepartners.com | C2: Priya | D2: Raman | E2: 46067 | F2: linkedin_organic | G2: brightlinepartners.com | H2: corporate | I2: Singapore | J2: 46083 | K2: 6 | L2: 4 | M2: 2 | N2: 46067 | O2: 46082 | P2: Study:2 | Q2: 3 | R2: Plus | S2: 1250 | T2: FALSE | U2: 0 | V2: 0 | X2: active | Y2: FALSE | Z2: FALSE | AA2: FALSE | AB2: TRUE | AC2: signup checkbox | AD2: 46067 | AE2: =IF(OR($N2="",$E2=""),"",IFERROR($N2-$E2,IFERROR(DATEVALUE($N2)-DATEVALUE($E2),""))) | AF2: =IF($A2="","",IF(OR(UPPER($Y2&"")="TRUE",UPPER($X2&"")="DELETED",UPPER($Z2&"")="TRUE",UPPER($AA2&"")="TRUE"),"S0",IF(UPPER($T2&"")="TRUE","S4",IF(N($M2)>=2,"S3",IF(N($M2)=1,"S2","S1")))))
AE3: =IF(OR($N3="",$E3=""),"",IFERROR($N3-$E3,IFERROR(DATEVALUE($N3)-DATEVALUE($E3),""))) | AF3: =IF($A3="","",IF(OR(UPPER($Y3&"")="TRUE",UPPER($X3&"")="DELETED",UPPER($Z3&"")="TRUE",UPPER($AA3&"")="TRUE"),"S0",IF(UPPER($T3&"")="TRUE","S4",IF(N($M3)>=2,"S3",IF(N($M3)=1,"S2","S1")))))
AE4: =IF(OR($N4="",$E4=""),"",IFERROR($N4-$E4,IFERROR(DATEVALUE($N4)-DATEVALUE($E4),""))) | AF4: =IF($A4="","",IF(OR(UPPER($Y4&"")="TRUE",UPPER($X4&"")="DELETED",UPPER($Z4&"")="TRUE",UPPER($AA4&"")="TRUE"),"S0",IF(UPPER($T4&"")="TRUE","S4",IF(N($M4)>=2,"S3",IF(N($M4)=1,"S2","S1")))))
AE5: =IF(OR($N5="",$E5=""),"",IFERROR($N5-$E5,IFERROR(DATEVALUE($N5)-DATEVALUE($E5),""))) | AF5: =IF($A5="","",IF(OR(UPPER($Y5&"")="TRUE",UPPER($X5&"")="DELETED",UPPER($Z5&"")="TRUE",UPPER($AA5&"")="TRUE"),"S0",IF(UPPER($T5&"")="TRUE","S4",IF(N($M5)>=2,"S3",IF(N($M5)=1,"S2","S1")))))
AE6: =IF(OR($N6="",$E6=""),"",IFERROR($N6-$E6,IFERROR(DATEVALUE($N6)-DATEVALUE($E6),""))) | AF6: =IF($A6="","",IF(OR(UPPER($Y6&"")="TRUE",UPPER($X6&"")="DELETED",UPPER($Z6&"")="TRUE",UPPER($AA6&"")="TRUE"),"S0",IF(UPPER($T6&"")="TRUE","S4",IF(N($M6)>=2,"S3",IF(N($M6)=1,"S2","S1")))))
AE7: =IF(OR($N7="",$E7=""),"",IFERROR($N7-$E7,IFERROR(DATEVALUE($N7)-DATEVALUE($E7),""))) | AF7: =IF($A7="","",IF(OR(UPPER($Y7&"")="TRUE",UPPER($X7&"")="DELETED",UPPER($Z7&"")="TRUE",UPPER($AA7&"")="TRUE"),"S0",IF(UPPER($T7&"")="TRUE","S4",IF(N($M7)>=2,"S3",IF(N($M7)=1,"S2","S1")))))
AE8: =IF(OR($N8="",$E8=""),"",IFERROR($N8-$E8,IFERROR(DATEVALUE($N8)-DATEVALUE($E8),""))) | AF8: =IF($A8="","",IF(OR(UPPER($Y8&"")="TRUE",UPPER($X8&"")="DELETED",UPPER($Z8&"")="TRUE",UPPER($AA8&"")="TRUE"),"S0",IF(UPPER($T8&"")="TRUE","S4",IF(N($M8)>=2,"S3",IF(N($M8)=1,"S2","S1")))))
AE9: =IF(OR($N9="",$E9=""),"",IFERROR($N9-$E9,IFERROR(DATEVALUE($N9)-DATEVALUE($E9),""))) | AF9: =IF($A9="","",IF(OR(UPPER($Y9&"")="TRUE",UPPER($X9&"")="DELETED",UPPER($Z9&"")="TRUE",UPPER($AA9&"")="TRUE"),"S0",IF(UPPER($T9&"")="TRUE","S4",IF(N($M9)>=2,"S3",IF(N($M9)=1,"S2","S1")))))
AE10: =IF(OR($N10="",$E10=""),"",IFERROR($N10-$E10,IFERROR(DATEVALUE($N10)-DATEVALUE($E10),""))) | AF10: =IF($A10="","",IF(OR(UPPER($Y10&"")="TRUE",UPPER($X10&"")="DELETED",UPPER($Z10&"")="TRUE",UPPER($AA10&"")="TRUE"),"S0",IF(UPPER($T10&"")="TRUE","S4",IF(N($M10)>=2,"S3",IF(N($M10)=1,"S2","S1")))))
AE11: =IF(OR($N11="",$E11=""),"",IFERROR($N11-$E11,IFERROR(DATEVALUE($N11)-DATEVALUE($E11),""))) | AF11: =IF($A11="","",IF(OR(UPPER($Y11&"")="TRUE",UPPER($X11&"")="DELETED",UPPER($Z11&"")="TRUE",UPPER($AA11&"")="TRUE"),"S0",IF(UPPER($T11&"")="TRUE","S4",IF(N($M11)>=2,"S3",IF(N($M11)=1,"S2","S1")))))
AE12: =IF(OR($N12="",$E12=""),"",IFERROR($N12-$E12,IFERROR(DATEVALUE($N12)-DATEVALUE($E12),""))) | AF12: =IF($A12="","",IF(OR(UPPER($Y12&"")="TRUE",UPPER($X12&"")="DELETED",UPPER($Z12&"")="TRUE",UPPER($AA12&"")="TRUE"),"S0",IF(UPPER($T12&"")="TRUE","S4",IF(N($M12)>=2,"S3",IF(N($M12)=1,"S2","S1")))))
AE13: =IF(OR($N13="",$E13=""),"",IFERROR($N13-$E13,IFERROR(DATEVALUE($N13)-DATEVALUE($E13),""))) | AF13: =IF($A13="","",IF(OR(UPPER($Y13&"")="TRUE",UPPER($X13&"")="DELETED",UPPER($Z13&"")="TRUE",UPPER($AA13&"")="TRUE"),"S0",IF(UPPER($T13&"")="TRUE","S4",IF(N($M13)>=2,"S3",IF(N($M13)=1,"S2","S1")))))
AE14: =IF(OR($N14="",$E14=""),"",IFERROR($N14-$E14,IFERROR(DATEVALUE($N14)-DATEVALUE($E14),""))) | AF14: =IF($A14="","",IF(OR(UPPER($Y14&"")="TRUE",UPPER($X14&"")="DELETED",UPPER($Z14&"")="TRUE",UPPER($AA14&"")="TRUE"),"S0",IF(UPPER($T14&"")="TRUE","S4",IF(N($M14)>=2,"S3",IF(N($M14)=1,"S2","S1")))))
... AE4000: =IF(OR($N4000="",$E4000=""),"",IFERROR($N4000-$E4000,IFERROR(DATEVALUE($N4000)-DATEVALUE($E4000),""))) | AF4000: =IF($A4000="","",IF(OR(UPPER($Y4000&"")="TRUE",UPPER($X4000&"")="DELETED",UPPER($Z4000&"")="TRUE",UPPER($AA4000&"")="TRUE"),"S0",IF(UPPER($T4000&"")="TRUE","S4",IF(N($M4000)>=2,"S3",IF(N($M4000)=1,"S2","S1")))))

Sheet Segment Summary
A1: Segment Summary
A2: Calculates itself from the User Export sheet. Nothing to fill in here.
A4: Population
A5: Total accounts exported | B5: =COUNTA('User Export'!$A$3:$A$4000) | C5: All rows, including test and deleted.
A6: S0 — Suppress | B6: =COUNTIF('User Export'!$AF$3:$AF$4000,"S0") | C6: Test, internal, deleted, hard-bounced or unsubscribed. Receives nothing.
A7: Addressable base | B7: =B5-B6 | C7: Everyone we can legitimately email.
A9: Send segments
A10: S1 — Never activated | B10: =COUNTIF('User Export'!$AF$3:$AF$4000,"S1") | C10: Zero completed analyses. The main target.
A11: S2 — Activated once | B11: =COUNTIF('User Export'!$AF$3:$AF$4000,"S2") | C11: Saw the output once and did not return.
A12: S3 — Repeat users | B12: =COUNTIF('User Export'!$AF$3:$AF$4000,"S3") | C12: Two or more. Testimonial and referral candidates.
A13: S4 — Ever paid | B13: =COUNTIF('User Export'!$AF$3:$AF$4000,"S4") | C13: Personal note from the founders before anything automated.
A14: Check — segments total | B14: =B10+B11+B12+B13 | C14: Must equal the addressable base.
A16: THE NUMBER
A17: Activated accounts | B17: =SUMPRODUCT(--('User Export'!$AF$3:$AF$4000<>"S0"),--('User Export'!$AF$3:$AF$4000<>""),--(ISNUMBER('User Export'!$M$3:$M$4000)),--('User Export'!$M$3:$M$4000>=1)) | C17: Addressable accounts with at least one completed analysis.
A18: ACTIVATION RATE | B18: =IFERROR(B17/B7,"—") | C18: The figure the entire GTM has been gated on since May.
A20: Supporting
A21: Median days signup to first analysis | B21: =IFERROR(MEDIAN('User Export'!$AE$3:$AE$4000),"—") | C21: Activated accounts only.
A22: Total analyses ever run | B22: =IFERROR(SUM('User Export'!$M$3:$M$4000),0)
A23: Analyses per activated account | B23: =IFERROR(B22/B17,"—")
A24: Accounts that ever paid | B24: =COUNTIF('User Export'!$AF$3:$AF$4000,"S4")

Sheet Domain Clusters
A1: Domain Clusters — company domains with 3 or more accounts
A2: A separate GROUP BY on email domain. Costs one query and may be the highest-value cut in this export.
A3: Trigger: three or more accounts on one corporate domain means a firm is already using Caspr individually,
A4: and can be converted to a pooled Enterprise budget. We have never looked. Exclude free-mail domains.
A6: email_domain | B6: account_count | C6: activated_count | D6: any_ever_paid | E6: earliest_signup
A7: brightlinepartners.com | B7: 4 | C7: 2 | D7: FALSE | E7: 46031

Sheet Data Dictionary
A1: Data Dictionary
A3: Column | B3: Type | C3: Required | D3: Definition
A4: user_id | B4: string | C4: Yes | D4: Internal identifier. Stable across systems.
A5: email | B5: string | C5: Yes | D5: Required to send.
A6: first_name | B6: string | C6: Yes | D6: For personalisation. Blank if never captured.
A7: last_name | B7: string
A8: signup_date | B8: date | C8: Yes | D8: Account creation date.
A9: signup_source | B9: string | D9: UTM source or referrer captured at signup. Blank if not captured.
A10: email_domain | B10: string | C10: Yes | D10: Everything after the @.
A11: email_domain_type | B11: enum | D11: corporate | free | edu | unknown
A12: country | B12: string | D12: From profile or signup IP, if held.
A13: last_login_date | B13: date | C13: Yes | D13: Blank if they never returned after signup.
A14: login_count | B14: integer | D14: Total sessions, if available.
A15: prompts_started | B15: integer | C15: Yes | D15: Times they began a prompt or conversation, whether or not it produced anything.
A16: analyses_completed | B16: integer | C16: Yes | D16: THE ACTIVATION NUMBER. Completed analyses that produced a deliverable.
A17: first_analysis_date | B17: date | C17: Yes | D17: Blank if none.
A18: last_analysis_date | B18: date | D18: Blank if none.
A19: analyses_by_depth | B19: string | D19: Counts by depth in whatever vocabulary the data uses. Legacy token tiers are fine — do not remap.
A20: reports_downloaded | B20: integer | D20: Any format.
A21: legacy_plan | B21: string | D21: Free / Plus / Pro under the retired token model.
A22: legacy_token_balance | B22: number | C22: Yes | D22: Unspent balance at export. Needed to decide what we owe people.
A23: ever_paid | B23: boolean | C23: Yes
A24: total_revenue_to_date | B24: number | C24: Yes | D24: USD.
A25: trial_balance_remaining | B25: number | D25: Under whatever model applies to that account.
A26: trial_expiry_date | B26: date
A27: account_status | B27: enum | C27: Yes | D27: active | deleted | suspended
A28: is_internal_or_test | B28: boolean | C28: Yes | D28: Staff, QA and demo accounts.
A29: email_hard_bounced | B29: boolean | C29: Yes | D29: Any prior hard bounce.
A30: unsubscribed | B30: boolean | C30: Yes | D30: Any prior opt-out.
A31: marketing_consent | B31: boolean | C31: Yes | D31: If recorded. If never separately recorded, leave blank and say so.
A32: consent_basis | B32: string | D32: e.g. signup checkbox, terms acceptance.
A33: consent_date | B33: date
A34: days_to_first_analysis | B34: calc | C34: — | D34: Calculated. Do not fill.
A35: segment | B35: calc | C35: — | D35: Calculated. S0 suppress · S1 never activated · S2 once · S3 repeat · S4 ever paid.
